pybuilder/LICENSE
pybuilder/__init__.py
pybuilder/ci_server_interaction.py
pybuilder/cli.py
pybuilder/core.py
pybuilder/errors.py
pybuilder/execution.py
pybuilder/graph_utils.py
pybuilder/install_utils.py
pybuilder/pep517.py
pybuilder/pip_common.py
pybuilder/pip_utils.py
pybuilder/pluginloader.py
pybuilder/python_env.py
pybuilder/python_utils.py
pybuilder/reactor.py
pybuilder/scaffolding.py
pybuilder/terminal.py
pybuilder/utils.py
pybuilder/vcs.py
pybuilder/_vendor/LICENSES
pybuilder/_vendor/__init__.py
pybuilder/_vendor/typing_extensions.py
pybuilder/_vendor/__pycache__/__init__.cpython-313.pyc
pybuilder/_vendor/_distutils_hack/__init__.py
pybuilder/_vendor/_distutils_hack/override.py
pybuilder/_vendor/autocommand/__init__.py
pybuilder/_vendor/autocommand/autoasync.py
pybuilder/_vendor/autocommand/autocommand.py
pybuilder/_vendor/autocommand/automain.py
pybuilder/_vendor/autocommand/autoparse.py
pybuilder/_vendor/autocommand/errors.py
pybuilder/_vendor/backports/__init__.py
pybuilder/_vendor/backports/tarfile/__init__.py
pybuilder/_vendor/backports/tarfile/__main__.py
pybuilder/_vendor/backports/tarfile/compat/__init__.py
pybuilder/_vendor/backports/tarfile/compat/py38.py
pybuilder/_vendor/colorama/__init__.py
pybuilder/_vendor/colorama/ansi.py
pybuilder/_vendor/colorama/ansitowin32.py
pybuilder/_vendor/colorama/initialise.py
pybuilder/_vendor/colorama/win32.py
pybuilder/_vendor/colorama/winterm.py
pybuilder/_vendor/colorama/tests/__init__.py
pybuilder/_vendor/colorama/tests/ansi_test.py
pybuilder/_vendor/colorama/tests/ansitowin32_test.py
pybuilder/_vendor/colorama/tests/initialise_test.py
pybuilder/_vendor/colorama/tests/isatty_test.py
pybuilder/_vendor/colorama/tests/utils.py
pybuilder/_vendor/colorama/tests/winterm_test.py
pybuilder/_vendor/distlib/__init__.py
pybuilder/_vendor/distlib/compat.py
pybuilder/_vendor/distlib/database.py
pybuilder/_vendor/distlib/index.py
pybuilder/_vendor/distlib/locators.py
pybuilder/_vendor/distlib/manifest.py
pybuilder/_vendor/importlib_metadata-8.7.0.dist-info/licenses/LICENSE
pybuilder/_vendor/virtualenv-20.34.0.dist-info/licenses/LICENSE
pybuilder-0.13.17.dist-info/METADATA
pybuilder-0.13.17.dist-info/WHEEL
pybuilder-0.13.17.dist-info/entry_points.txt
pybuilder-0.13.17.dist-info/namespace_packages.txt
pybuilder-0.13.17.dist-info/top_level.txt
pybuilder-0.13.17.dist-info/zip-safe
pybuilder/_vendor/importlib_metadata-8.7.0.dist-info/INSTALLER
pybuilder/_vendor/importlib_metadata-8.7.0.dist-info/METADATA
pybuilder/_vendor/importlib_metadata-8.7.0.dist-info/RECORD
pybuilder/_vendor/importlib_metadata-8.7.0.dist-info/REQUESTED
pybuilder/_vendor/importlib_metadata-8.7.0.dist-info/WHEEL
pybuilder/_vendor/importlib_metadata-8.7.0.dist-info/top_level.txt
pybuilder/_vendor/virtualenv-20.34.0.dist-info/INSTALLER
pybuilder/_vendor/virtualenv-20.34.0.dist-info/METADATA
pybuilder/_vendor/virtualenv-20.34.0.dist-info/RECORD
pybuilder/_vendor/virtualenv-20.34.0.dist-info/REQUESTED
pybuilder/_vendor/virtualenv-20.34.0.dist-info/WHEEL
pybuilder/_vendor/virtualenv-20.34.0.dist-info/entry_points.txt
pybuilder-0.13.17.dist-info/RECORD
